{
	"name": "ds_ToreadDataFromGit",
	"properties": {
		"linkedServiceName": {
			"referenceName": "ls_httptoLoadFilesfrom Git",
			"type": "LinkedServiceReference"
		},
		"parameters": {
			"RelativeURL": {
				"type": "string"
			}
		},
		"annotations": [],
		"type": "DelimitedText",
		"typeProperties": {
			"location": {
				"type": "HttpServerLocation",
				"relativeUrl": {
					"value": "@dataset().RelativeURL",
					"type": "Expression"
				}
			},
			"columnDelimiter": ",",
			"escapeChar": "\\",
			"firstRowAsHeader": true,
			"quoteChar": "\""
		},
		"schema": [
			{
				"name": "country",
				"type": "String"
			},
			{
				"name": "country_code",
				"type": "String"
			},
			{
				"name": "year_week",
				"type": "String"
			},
			{
				"name": "new_cases",
				"type": "String"
			},
			{
				"name": "tests_done",
				"type": "String"
			},
			{
				"name": "population",
				"type": "String"
			},
			{
				"name": "testing_rate",
				"type": "String"
			},
			{
				"name": "positivity_rate",
				"type": "String"
			},
			{
				"name": "testing_data_source",
				"type": "String"
			}
		]
	},
	"type": "Microsoft.DataFactory/factories/datasets"
}